{"digest":"074016fee4b2b1ab6fa82b0713449193e9f42e13","css":"atom-workspace {\n  font-family: Inter Medium;\n}\nhtml,\nbody,\n.tree-view,\n.tab-bar .tab {\n  font-size: 13px;\n}\n.tab-bar {\n  overflow-x: hidden;\n  display: flex;\n  flex-wrap: wrap;\n}\n.tab-bar .tab {\n  min-width: 150px;\n  flex: 1;\n  display: flex;\n  flex-wrap: wrap;\n  justify-content: center;\n}\n.tab-bar .tab .title {\n  flex: 1 1 16px;\n  text-overflow: ellipsis;\n  text-align: center;\n}\n.tab-bar .tab .close-icon {\n  position: right;\n}\n.tab-bar .tab.active {\n  flex: 1;\n  width: initial;\n}\n.tab-bar .tab.active:hover .close-icon {\n  position: right;\n}\n","imports":[{"path":"static/variables/ui-variables.less","digest":"b28ed6c38c4cfce23f83a1b012a3968aa63fce4c"},{"path":"static/variables/syntax-variables.less","digest":"812c1b7883a023f768773d14294653adcdb932d7"}],"version":1}